easy_async_tg_notify/__init__.py
easy_async_tg_notify/notifier.py
easy_async_tg_notify-0.1.dist-info/METADATA
easy_async_tg_notify-0.1.dist-info/WHEEL
easy_async_tg_notify-0.1.dist-info/top_level.txt
easy_async_tg_notify-0.1.dist-info/RECORD
