Metadata-Version: 2.1
Name: easy_async_tg_notify
Version: 0.1
Summary: Asynchronous Telegram notification sender
Home-page: https://github.com/Yakvenalex/easy_async_tg_notify
Author: Alexey Yakovenko
Author-email: mr.mnogo@gmail.com
Classifier: Programming Language :: Python :: 3
Classifier: License :: OSI Approved :: MIT License
Classifier: Operating System :: OS Independent
Requires-Python: >=3.6
Requires-Dist: httpx
Requires-Dist: python-decouple
Requires-Dist: aiofiles
